{
    "Variables":  {
                      "DemoWebServer-DomainJoinCredName":  {
                                                               "isEncrypted":  false,
                                                               "Description":  "",
                                                               "Value":  "omsa@scorchdev.com"
                                                           },
                      "DemoWebServer-NuGetCredentialName":  {
                                                                "isEncrypted":  false,
                                                                "Description":  "",
                                                                "Value":  "Ryan.Andorfer"
                                                            },
                      "DemoWebServer-Domain":  {
                                                   "isEncrypted":  false,
                                                   "Description":  "",
                                                   "Value":  "SCOrchDev.com"
                                               }
                  }
}
